{
  "hash": "8f375ac3",
  "configHash": "1a07f069",
  "lockfileHash": "860deab4",
  "browserHash": "d5848f6c",
  "optimized": {
    "@headlessui/react": {
      "src": "../../node_modules/@headlessui/react/dist/headlessui.esm.js",
      "file": "@headlessui_react.js",
      "fileHash": "bd752c8f",
      "needsInterop": false
    },
    "@heroicons/react/24/outline": {
      "src": "../../node_modules/@heroicons/react/24/outline/esm/index.js",
      "file": "@heroicons_react_24_outline.js",
      "fileHash": "7ee3de92",
      "needsInterop": false
    },
    "react": {
      "src": "../../node_modules/react/index.js",
      "file": "react.js",
      "fileHash": "06676917",
      "needsInterop": true
    },
    "react-dom/client": {
      "src": "../../node_modules/react-dom/client.js",
      "file": "react-dom_client.js",
      "fileHash": "adf13dea",
      "needsInterop": true
    },
    "react-router-dom": {
      "src": "../../node_modules/react-router-dom/dist/index.mjs",
      "file": "react-router-dom.js",
      "fileHash": "47d55f58",
      "needsInterop": false
    },
    "react-to-print": {
      "src": "../../node_modules/react-to-print/lib/index.js",
      "file": "react-to-print.js",
      "fileHash": "24d4949b",
      "needsInterop": true
    },
    "recharts": {
      "src": "../../node_modules/recharts/es6/index.js",
      "file": "recharts.js",
      "fileHash": "a1e965ea",
      "needsInterop": false
    }
  },
  "chunks": {
    "chunk-2KHBIA62": {
      "file": "chunk-2KHBIA62.js"
    },
    "chunk-WEJJOBXA": {
      "file": "chunk-WEJJOBXA.js"
    },
    "chunk-VCDLJVZS": {
      "file": "chunk-VCDLJVZS.js"
    }
  }
}